public_domains.py
public_domains-0.0.8.dist-info/LICENSE.txt
public_domains-0.0.8.dist-info/METADATA
public_domains-0.0.8.dist-info/WHEEL
public_domains-0.0.8.dist-info/entry_points.txt
public_domains-0.0.8.dist-info/top_level.txt
public_domains-0.0.8.dist-info/RECORD
