Metadata-Version: 2.1
Name: public-domains
Version: 0.0.8
Summary: Find possible host names in a source text
Home-page: https://github.com/edsu/public_domains
Author: Ed Summers
Author-email: ehs@pobox.com
License: MIT
Platform: UNKNOWN
Classifier: License :: OSI Approved :: MIT License
Requires-Python: >=2.7
License-File: LICENSE.txt
Requires-Dist: nltk
Requires-Dist: tqdm
Requires-Dist: requests
Requires-Dist: python-whois
